{
  "ConnectionStrings": {
    "DefaultConnection": "server=127.0.0.1; Port=3306; database=NetCars;user=root;password=root"
  },

  //Dawid= server=127.0.0.1; Port=3306; database=NetCars;user=root;password=root"
  //Marcin= "Data Source=NetCars.db"

  "CloudinarySettings": {
    "CloudName": "netcars",
    "ApiKey": "271549582381252",
    "ApiSecret": "ROr-oTzT-oxJdKdimvo_AuiUVtE"
  },

  "Authentication:Facebook:AppId": "AppId - 855139225098776",
  "Authentication:Facebook:AppSecret": "AppSecret - 43d6ecaf6e15548ef6017f85c143eb70"

}

//Tutaj ustawiacie połączenie z bazą danych. Polecam korzystanie z MySQL Workbench, bo jest lekki i ma wszystkie niezbędne narzędzia.

// Do Cloudinary trzeba stworzyć konto. Cloudinary to serwis to przechowywania zdjęć. Będziemy tam wrzucać zdjęcia samochodów